kabbes_client/Package.json
kabbes_client/Package.py
kabbes_client/Root.json
kabbes_client/Root.py
kabbes_client/__init__.py
kabbes_client/__main__.py
kabbes_client-0.5.0.dist-info/LICENSE
kabbes_client-0.5.0.dist-info/METADATA
kabbes_client-0.5.0.dist-info/WHEEL
kabbes_client-0.5.0.dist-info/top_level.txt
kabbes_client-0.5.0.dist-info/RECORD
