Metadata-Version: 2.1
Name: kabbes-client
Version: 0.5.0
Summary: Unnamed repository; edit this file 'description' to name the repository.
Home-page: https://pypi.org/project/kabbes-client
Author: James Kabbes
Author-email: james.kabbes@gmail.com
Project-URL: GitHub, https://github.com/jameskabbes/config
Project-URL: Documentation, https://jameskabbes.github.io/config
Classifier: Programming Language :: Python :: 3
Classifier: License :: OSI Approved :: MIT License
Classifier: Operating System :: OS Independent
Requires-Python: >=3.7
License-File: LICENSE
Requires-Dist: kabbes-parent-class
Requires-Dist: kabbes-config
Requires-Dist: kabbes-dir-ops
Requires-Dist: kabbes-py-starter
Requires-Dist: xdg
